{
  "lookup": {
    "rules": {
      "[{\"prev_action\": {\"action_name\": \"action_listen\"}, \"user\": {\"intent\": \"goodbye\"}}]": "utter_goodbye",
      "[{\"prev_action\": {\"action_name\": \"action_listen\"}, \"user\": {\"intent\": \"goodbye\"}}, {\"prev_action\": {\"action_name\": \"utter_goodbye\"}, \"user\": {\"intent\": \"goodbye\"}}]": "action_listen",
      "[{\"prev_action\": {\"action_name\": \"action_listen\"}, \"user\": {\"intent\": \"automotive_business\"}}]": "action_automotive_specialist",
      "[{\"prev_action\": {\"action_name\": \"action_listen\"}, \"user\": {\"intent\": \"automotive_business\"}}, {\"prev_action\": {\"action_name\": \"action_automotive_specialist\"}, \"user\": {\"intent\": \"automotive_business\"}}]": "action_listen",
      "[{\"prev_action\": {\"action_name\": \"action_listen\"}, \"user\": {\"intent\": \"ask_implementation_timeline\"}}]": "action_implementation_timeline",
      "[{\"prev_action\": {\"action_name\": \"action_listen\"}, \"user\": {\"intent\": \"ask_implementation_timeline\"}}, {\"prev_action\": {\"action_name\": \"action_implementation_timeline\"}, \"user\": {\"intent\": \"ask_implementation_timeline\"}}]": "action_listen",
      "[{\"prev_action\": {\"action_name\": \"action_listen\"}, \"user\": {\"intent\": \"ask_compliance\"}}]": "action_compliance_details",
      "[{\"prev_action\": {\"action_name\": \"action_listen\"}, \"user\": {\"intent\": \"ask_compliance\"}}, {\"prev_action\": {\"action_name\": \"action_compliance_details\"}, \"user\": {\"intent\": \"ask_compliance\"}}]": "action_listen",
      "[{\"prev_action\": {\"action_name\": \"action_listen\"}, \"user\": {\"intent\": \"schedule_veteran_consultation\"}}]": "action_schedule_veteran_consultation",
      "[{\"prev_action\": {\"action_name\": \"action_listen\"}, \"user\": {\"intent\": \"schedule_veteran_consultation\"}}, {\"prev_action\": {\"action_name\": \"action_schedule_veteran_consultation\"}, \"user\": {\"intent\": \"schedule_veteran_consultation\"}}]": "action_listen",
      "[{\"prev_action\": {\"action_name\": \"action_listen\"}, \"user\": {\"intent\": \"out_of_scope\"}}]": "utter_out_of_scope",
      "[{\"prev_action\": {\"action_name\": \"action_listen\"}, \"user\": {\"intent\": \"out_of_scope\"}}, {\"prev_action\": {\"action_name\": \"utter_out_of_scope\"}, \"user\": {\"intent\": \"out_of_scope\"}}]": "action_listen",
      "[{\"prev_action\": {\"action_name\": \"action_listen\"}, \"user\": {\"intent\": \"schedule_demo\"}}]": "action_schedule_demo",
      "[{\"prev_action\": {\"action_name\": \"action_listen\"}, \"user\": {\"intent\": \"schedule_demo\"}}, {\"prev_action\": {\"action_name\": \"action_schedule_demo\"}, \"user\": {\"intent\": \"schedule_demo\"}}]": "action_listen",
      "[{\"prev_action\": {\"action_name\": \"action_listen\"}, \"user\": {\"intent\": \"start_free_trial\"}}]": "action_start_free_trial",
      "[{\"prev_action\": {\"action_name\": \"action_listen\"}, \"user\": {\"intent\": \"start_free_trial\"}}, {\"prev_action\": {\"action_name\": \"action_start_free_trial\"}, \"user\": {\"intent\": \"start_free_trial\"}}]": "action_listen",
      "[{\"prev_action\": {\"action_name\": \"action_listen\"}, \"user\": {\"intent\": \"ask_integration\"}}]": "action_integration_details",
      "[{\"prev_action\": {\"action_name\": \"action_listen\"}, \"user\": {\"intent\": \"ask_integration\"}}, {\"prev_action\": {\"action_name\": \"action_integration_details\"}, \"user\": {\"intent\": \"ask_integration\"}}]": "action_listen",
      "[{\"prev_action\": {\"action_name\": \"action_listen\"}, \"user\": {\"intent\": \"customer_retention\"}}]": "action_customer_retention",
      "[{\"prev_action\": {\"action_name\": \"action_listen\"}, \"user\": {\"intent\": \"customer_retention\"}}, {\"prev_action\": {\"action_name\": \"action_customer_retention\"}, \"user\": {\"intent\": \"customer_retention\"}}]": "action_listen",
      "[{\"prev_action\": {\"action_name\": \"action_listen\"}, \"user\": {\"intent\": \"ask_contact_info\"}}]": "action_contact_info",
      "[{\"prev_action\": {\"action_name\": \"action_listen\"}, \"user\": {\"intent\": \"ask_contact_info\"}}, {\"prev_action\": {\"action_name\": \"action_contact_info\"}, \"user\": {\"intent\": \"ask_contact_info\"}}]": "action_listen",
      "[{\"prev_action\": {\"action_name\": \"action_listen\"}, \"user\": {\"intent\": \"affirm\"}}]": "utter_affirm",
      "[{\"prev_action\": {\"action_name\": \"action_listen\"}, \"user\": {\"intent\": \"affirm\"}}, {\"prev_action\": {\"action_name\": \"utter_affirm\"}, \"user\": {\"intent\": \"affirm\"}}]": "action_listen",
      "[{\"prev_action\": {\"action_name\": \"action_listen\"}, \"user\": {\"intent\": \"pricing_inquiry\"}}]": "action_pricing_inquiry",
      "[{\"prev_action\": {\"action_name\": \"action_listen\"}, \"user\": {\"intent\": \"pricing_inquiry\"}}, {\"prev_action\": {\"action_name\": \"action_pricing_inquiry\"}, \"user\": {\"intent\": \"pricing_inquiry\"}}]": "action_listen",
      "[{\"prev_action\": {\"action_name\": \"action_listen\"}, \"user\": {\"intent\": \"ask_support_hours\"}}]": "action_support_hours",
      "[{\"prev_action\": {\"action_name\": \"action_listen\"}, \"user\": {\"intent\": \"ask_support_hours\"}}, {\"prev_action\": {\"action_name\": \"action_support_hours\"}, \"user\": {\"intent\": \"ask_support_hours\"}}]": "action_listen",
      "[{\"prev_action\": {\"action_name\": \"action_session_start\"}}]": "action_listen",
      "[{\"prev_action\": {\"action_name\": \"action_listen\"}, \"user\": {\"intent\": \"veteran_discounts\"}}]": "action_veteran_discounts",
      "[{\"prev_action\": {\"action_name\": \"action_listen\"}, \"user\": {\"intent\": \"veteran_discounts\"}}, {\"prev_action\": {\"action_name\": \"action_veteran_discounts\"}, \"user\": {\"intent\": \"veteran_discounts\"}}]": "action_listen",
      "[{\"prev_action\": {\"action_name\": \"action_listen\"}, \"user\": {\"intent\": \"retail_business\"}}]": "action_retail_specialist",
      "[{\"prev_action\": {\"action_name\": \"action_listen\"}, \"user\": {\"intent\": \"retail_business\"}}, {\"prev_action\": {\"action_name\": \"action_retail_specialist\"}, \"user\": {\"intent\": \"retail_business\"}}]": "action_listen",
      "[{\"prev_action\": {\"action_name\": \"action_listen\"}, \"user\": {\"intent\": \"nlu_fallback\"}}]": "utter_ask_clarification",
      "[{\"prev_action\": {\"action_name\": \"action_listen\"}, \"user\": {\"intent\": \"nlu_fallback\"}}, {\"prev_action\": {\"action_name\": \"utter_ask_clarification\"}, \"user\": {\"intent\": \"nlu_fallback\"}}]": "action_listen",
      "[{\"prev_action\": {\"action_name\": \"action_listen\"}, \"user\": {\"intent\": \"ask_security\"}}]": "action_security_details",
      "[{\"prev_action\": {\"action_name\": \"action_listen\"}, \"user\": {\"intent\": \"ask_security\"}}, {\"prev_action\": {\"action_name\": \"action_security_details\"}, \"user\": {\"intent\": \"ask_security\"}}]": "action_listen",
      "[{\"prev_action\": {\"action_name\": \"action_listen\"}, \"user\": {\"intent\": \"greet\"}}]": "utter_greet",
      "[{\"prev_action\": {\"action_name\": \"action_listen\"}, \"user\": {\"intent\": \"greet\"}}, {\"prev_action\": {\"action_name\": \"utter_greet\"}, \"user\": {\"intent\": \"greet\"}}]": "action_listen",
      "[{\"prev_action\": {\"action_name\": \"action_listen\"}, \"user\": {\"intent\": \"restaurant_business\"}}]": "action_restaurant_specialist",
      "[{\"prev_action\": {\"action_name\": \"action_listen\"}, \"user\": {\"intent\": \"restaurant_business\"}}, {\"prev_action\": {\"action_name\": \"action_restaurant_specialist\"}, \"user\": {\"intent\": \"restaurant_business\"}}]": "action_listen",
      "[{\"prev_action\": {\"action_name\": \"action_listen\"}, \"user\": {\"intent\": \"business_analysis\"}}]": "action_business_analysis",
      "[{\"prev_action\": {\"action_name\": \"action_listen\"}, \"user\": {\"intent\": \"business_analysis\"}}, {\"prev_action\": {\"action_name\": \"action_business_analysis\"}, \"user\": {\"intent\": \"business_analysis\"}}]": "action_listen",
      "[{\"prev_action\": {\"action_name\": \"action_listen\"}, \"user\": {\"intent\": \"deny\"}}]": "utter_deny",
      "[{\"prev_action\": {\"action_name\": \"action_listen\"}, \"user\": {\"intent\": \"deny\"}}, {\"prev_action\": {\"action_name\": \"utter_deny\"}, \"user\": {\"intent\": \"deny\"}}]": "action_listen",
      "[{\"prev_action\": {\"action_name\": \"action_listen\"}, \"user\": {\"intent\": \"technical_details\"}}]": "action_technical_details",
      "[{\"prev_action\": {\"action_name\": \"action_listen\"}, \"user\": {\"intent\": \"technical_details\"}}, {\"prev_action\": {\"action_name\": \"action_technical_details\"}, \"user\": {\"intent\": \"technical_details\"}}]": "action_listen",
      "[{\"prev_action\": {\"action_name\": \"action_listen\"}, \"user\": {\"intent\": \"business_consultation\"}}]": "utter_business_consultation",
      "[{\"prev_action\": {\"action_name\": \"action_listen\"}, \"user\": {\"intent\": \"business_consultation\"}}, {\"prev_action\": {\"action_name\": \"utter_business_consultation\"}, \"user\": {\"intent\": \"business_consultation\"}}]": "action_listen",
      "[{\"prev_action\": {\"action_name\": \"action_listen\"}, \"user\": {\"intent\": \"healthcare_business\"}}]": "action_healthcare_specialist",
      "[{\"prev_action\": {\"action_name\": \"action_listen\"}, \"user\": {\"intent\": \"healthcare_business\"}}, {\"prev_action\": {\"action_name\": \"action_healthcare_specialist\"}, \"user\": {\"intent\": \"healthcare_business\"}}]": "action_listen"
    },
    "rule_only_slots": [],
    "rule_only_loops": [],
    "rules_for_loop_unhappy_path": {},
    "rules_not_in_stories": [
      "predicting default action with intent restart",
      "predicting default action with intent back",
      "[{\"prev_action\": {\"action_name\": \"action_session_start\"}}]",
      "predicting default action with intent session_start"
    ]
  }
}